{
  "stock_no": "1727",
  "year_month": "202511",
  "daily_data": [
    {
      "date": "114/11/03",
      "volume": 1038003,
      "amount": 36053546,
      "open": 35.2,
      "high": 35.2,
      "low": 34.5,
      "close": 34.55,
      "change": -0.65,
      "transactions": 1021,
      "note": ""
    },
    {
      "date": "114/11/04",
      "volume": 1088447,
      "amount": 37151308,
      "open": 34.5,
      "high": 34.7,
      "low": 33.85,
      "close": 34.0,
      "change": -0.55,
      "transactions": 843,
      "note": ""
    },
    {
      "date": "114/11/05",
      "volume": 768224,
      "amount": 25828628,
      "open": 33.5,
      "high": 34.25,
      "low": 33.2,
      "close": 34.2,
      "change": 0.2,
      "transactions": 675,
      "note": ""
    },
    {
      "date": "114/11/06",
      "volume": 2738474,
      "amount": 98764804,
      "open": 34.45,
      "high": 37.0,
      "low": 34.2,
      "close": 36.25,
      "change": 2.05,
      "transactions": 2068,
      "note": ""
    },
    {
      "date": "114/11/07",
      "volume": 1056776,
      "amount": 37084121,
      "open": 36.0,
      "high": 36.05,
      "low": 34.6,
      "close": 34.85,
      "change": -1.4,
      "transactions": 1608,
      "note": ""
    },
    {
      "date": "114/11/10",
      "volume": 799515,
      "amount": 28240483,
      "open": 35.0,
      "high": 35.85,
      "low": 34.65,
      "close": 35.7,
      "change": 0.85,
      "transactions": 670,
      "note": ""
    },
    {
      "date": "114/11/11",
      "volume": 4230659,
      "amount": 157048657,
      "open": 35.05,
      "high": 38.0,
      "low": 35.05,
      "close": 37.3,
      "change": 1.6,
      "transactions": 3283,
      "note": ""
    },
    {
      "date": "114/11/12",
      "volume": 2300183,
      "amount": 86469072,
      "open": 37.2,
      "high": 38.1,
      "low": 37.0,
      "close": 37.5,
      "change": 0.2,
      "transactions": 1846,
      "note": ""
    },
    {
      "date": "114/11/13",
      "volume": 1458992,
      "amount": 53607807,
      "open": 37.3,
      "high": 37.3,
      "low": 36.2,
      "close": 37.3,
      "change": -0.2,
      "transactions": 1819,
      "note": ""
    },
    {
      "date": "114/11/14",
      "volume": 2825599,
      "amount": 105924318,
      "open": 36.55,
      "high": 37.95,
      "low": 36.5,
      "close": 37.5,
      "change": 0.2,
      "transactions": 1636,
      "note": ""
    },
    {
      "date": "114/11/17",
      "volume": 15142840,
      "amount": 611798208,
      "open": 37.6,
      "high": 41.25,
      "low": 37.3,
      "close": 40.3,
      "change": 2.8,
      "transactions": 9830,
      "note": ""
    },
    {
      "date": "114/11/18",
      "volume": 6538988,
      "amount": 255697485,
      "open": 40.5,
      "high": 40.7,
      "low": 37.8,
      "close": 37.85,
      "change": -2.45,
      "transactions": 6950,
      "note": ""
    },
    {
      "date": "114/11/19",
      "volume": 3999741,
      "amount": 153463683,
      "open": 37.85,
      "high": 39.7,
      "low": 36.7,
      "close": 38.8,
      "change": 0.95,
      "transactions": 3783,
      "note": ""
    },
    {
      "date": "114/11/20",
      "volume": 6679002,
      "amount": 264615351,
      "open": 39.9,
      "high": 41.0,
      "low": 38.9,
      "close": 39.2,
      "change": 0.4,
      "transactions": 7130,
      "note": ""
    },
    {
      "date": "114/11/21",
      "volume": 3557382,
      "amount": 132401184,
      "open": 37.0,
      "high": 38.6,
      "low": 36.5,
      "close": 37.05,
      "change": -2.15,
      "transactions": 4956,
      "note": ""
    },
    {
      "date": "114/11/24",
      "volume": 10400363,
      "amount": 412478641,
      "open": 37.45,
      "high": 40.75,
      "low": 37.45,
      "close": 40.25,
      "change": 3.2,
      "transactions": 7658,
      "note": ""
    },
    {
      "date": "114/11/25",
      "volume": 16065720,
      "amount": 700115186,
      "open": 41.75,
      "high": 44.25,
      "low": 41.3,
      "close": 44.25,
      "change": 4.0,
      "transactions": 7761,
      "note": ""
    },
    {
      "date": "114/11/26",
      "volume": 34439461,
      "amount": 1492653759,
      "open": 45.9,
      "high": 46.4,
      "low": 39.85,
      "close": 39.85,
      "change": -4.4,
      "transactions": 23055,
      "note": ""
    },
    {
      "date": "114/11/27",
      "volume": 14868497,
      "amount": 588344144,
      "open": 39.0,
      "high": 40.8,
      "low": 37.85,
      "close": 40.55,
      "change": 0.7,
      "transactions": 9103,
      "note": ""
    },
    {
      "date": "114/11/28",
      "volume": 12078380,
      "amount": 481314148,
      "open": 40.1,
      "high": 41.15,
      "low": 38.25,
      "close": 41.15,
      "change": 0.6,
      "transactions": 8958,
      "note": ""
    }
  ]
}