{
  "stock_no": "1417",
  "year_month": "202503",
  "daily_data": [
    {
      "date": "114/03/03",
      "volume": 81605,
      "amount": 757509,
      "open": 9.36,
      "high": 9.36,
      "low": 9.23,
      "close": 9.23,
      "change": -0.15,
      "transactions": 188,
      "note": ""
    },
    {
      "date": "114/03/04",
      "volume": 107402,
      "amount": 987520,
      "open": 9.23,
      "high": 9.29,
      "low": 9.15,
      "close": 9.22,
      "change": -0.01,
      "transactions": 208,
      "note": ""
    },
    {
      "date": "114/03/05",
      "volume": 81082,
      "amount": 752969,
      "open": 9.32,
      "high": 9.32,
      "low": 9.22,
      "close": 9.26,
      "change": 0.04,
      "transactions": 119,
      "note": ""
    },
    {
      "date": "114/03/06",
      "volume": 47680,
      "amount": 441947,
      "open": 9.32,
      "high": 9.32,
      "low": 9.21,
      "close": 9.26,
      "change": 0.0,
      "transactions": 342,
      "note": ""
    },
    {
      "date": "114/03/07",
      "volume": 133293,
      "amount": 1223710,
      "open": 9.27,
      "high": 9.27,
      "low": 9.14,
      "close": 9.23,
      "change": -0.03,
      "transactions": 1122,
      "note": ""
    },
    {
      "date": "114/03/10",
      "volume": 37608,
      "amount": 346508,
      "open": 9.28,
      "high": 9.28,
      "low": 9.19,
      "close": 9.19,
      "change": -0.04,
      "transactions": 872,
      "note": ""
    },
    {
      "date": "114/03/11",
      "volume": 319669,
      "amount": 2956529,
      "open": 9.27,
      "high": 9.38,
      "low": 9.08,
      "close": 9.28,
      "change": 0.09,
      "transactions": 717,
      "note": ""
    },
    {
      "date": "114/03/12",
      "volume": 118544,
      "amount": 1098488,
      "open": 9.37,
      "high": 9.37,
      "low": 9.2,
      "close": 9.27,
      "change": -0.01,
      "transactions": 581,
      "note": ""
    },
    {
      "date": "114/03/13",
      "volume": 79079,
      "amount": 730702,
      "open": 9.31,
      "high": 9.35,
      "low": 9.15,
      "close": 9.15,
      "change": -0.12,
      "transactions": 578,
      "note": ""
    },
    {
      "date": "114/03/14",
      "volume": 88046,
      "amount": 808816,
      "open": 9.15,
      "high": 9.23,
      "low": 9.15,
      "close": 9.22,
      "change": 0.07,
      "transactions": 458,
      "note": ""
    },
    {
      "date": "114/03/17",
      "volume": 130415,
      "amount": 1218123,
      "open": 9.3,
      "high": 9.38,
      "low": 9.25,
      "close": 9.34,
      "change": 0.12,
      "transactions": 1034,
      "note": ""
    },
    {
      "date": "114/03/18",
      "volume": 134661,
      "amount": 1264423,
      "open": 9.4,
      "high": 9.43,
      "low": 9.35,
      "close": 9.4,
      "change": 0.06,
      "transactions": 657,
      "note": ""
    },
    {
      "date": "114/03/19",
      "volume": 207068,
      "amount": 1949381,
      "open": 9.44,
      "high": 9.44,
      "low": 9.38,
      "close": 9.43,
      "change": 0.03,
      "transactions": 921,
      "note": ""
    },
    {
      "date": "114/03/20",
      "volume": 144601,
      "amount": 1363445,
      "open": 9.42,
      "high": 9.5,
      "low": 9.33,
      "close": 9.46,
      "change": 0.03,
      "transactions": 545,
      "note": ""
    },
    {
      "date": "114/03/21",
      "volume": 181875,
      "amount": 1715485,
      "open": 9.44,
      "high": 9.49,
      "low": 9.38,
      "close": 9.41,
      "change": -0.05,
      "transactions": 275,
      "note": ""
    },
    {
      "date": "114/03/24",
      "volume": 166064,
      "amount": 1569076,
      "open": 9.47,
      "high": 9.56,
      "low": 9.32,
      "close": 9.45,
      "change": 0.04,
      "transactions": 268,
      "note": ""
    },
    {
      "date": "114/03/25",
      "volume": 134794,
      "amount": 1270090,
      "open": 9.45,
      "high": 9.5,
      "low": 9.31,
      "close": 9.45,
      "change": 0.0,
      "transactions": 196,
      "note": ""
    },
    {
      "date": "114/03/26",
      "volume": 163718,
      "amount": 1526549,
      "open": 9.31,
      "high": 9.44,
      "low": 9.25,
      "close": 9.35,
      "change": -0.1,
      "transactions": 209,
      "note": ""
    },
    {
      "date": "114/03/27",
      "volume": 61882,
      "amount": 577445,
      "open": 9.35,
      "high": 9.4,
      "low": 9.28,
      "close": 9.4,
      "change": 0.05,
      "transactions": 142,
      "note": ""
    },
    {
      "date": "114/03/28",
      "volume": 189170,
      "amount": 1748304,
      "open": 9.31,
      "high": 9.42,
      "low": 9.14,
      "close": 9.21,
      "change": -0.19,
      "transactions": 221,
      "note": ""
    },
    {
      "date": "114/03/31",
      "volume": 278180,
      "amount": 2475090,
      "open": 9.18,
      "high": 9.2,
      "low": 8.7,
      "close": 8.87,
      "change": -0.34,
      "transactions": 359,
      "note": ""
    }
  ]
}