{
  "stock_no": "2451",
  "year_month": "202507",
  "daily_data": [
    {
      "date": "114/07/01",
      "volume": 5020892,
      "amount": 512178063,
      "open": 101.0,
      "high": 103.0,
      "low": 100.5,
      "close": 102.5,
      "change": 2.0,
      "transactions": 2680,
      "note": ""
    },
    {
      "date": "114/07/02",
      "volume": 5902959,
      "amount": 608799328,
      "open": 102.5,
      "high": 105.0,
      "low": 100.5,
      "close": 105.0,
      "change": 2.5,
      "transactions": 2918,
      "note": ""
    },
    {
      "date": "114/07/03",
      "volume": 13425319,
      "amount": 1502631960,
      "open": 105.0,
      "high": 115.0,
      "low": 103.5,
      "close": 114.5,
      "change": 9.5,
      "transactions": 9936,
      "note": ""
    },
    {
      "date": "114/07/04",
      "volume": 13453980,
      "amount": 1578820220,
      "open": 113.5,
      "high": 120.0,
      "low": 111.5,
      "close": 120.0,
      "change": 5.5,
      "transactions": 7934,
      "note": ""
    },
    {
      "date": "114/07/07",
      "volume": 7118611,
      "amount": 810833198,
      "open": 120.0,
      "high": 122.0,
      "low": 108.5,
      "close": 111.0,
      "change": -9.0,
      "transactions": 7366,
      "note": ""
    },
    {
      "date": "114/07/08",
      "volume": 6018811,
      "amount": 611180361,
      "open": 103.5,
      "high": 105.0,
      "low": 99.3,
      "close": 100.5,
      "change": 0.0,
      "transactions": 4279,
      "note": ""
    },
    {
      "date": "114/07/09",
      "volume": 2431879,
      "amount": 242596633,
      "open": 99.9,
      "high": 101.0,
      "low": 98.9,
      "close": 99.9,
      "change": -0.6,
      "transactions": 2262,
      "note": ""
    },
    {
      "date": "114/07/10",
      "volume": 2269182,
      "amount": 221931789,
      "open": 100.0,
      "high": 100.5,
      "low": 96.9,
      "close": 96.9,
      "change": -3.0,
      "transactions": 2524,
      "note": ""
    },
    {
      "date": "114/07/11",
      "volume": 2622593,
      "amount": 255187668,
      "open": 96.9,
      "high": 98.1,
      "low": 96.8,
      "close": 96.8,
      "change": -0.1,
      "transactions": 2112,
      "note": ""
    },
    {
      "date": "114/07/14",
      "volume": 1064495,
      "amount": 102330067,
      "open": 97.0,
      "high": 97.2,
      "low": 95.2,
      "close": 96.3,
      "change": -0.5,
      "transactions": 1386,
      "note": ""
    },
    {
      "date": "114/07/15",
      "volume": 5506484,
      "amount": 508875849,
      "open": 95.8,
      "high": 96.4,
      "low": 90.8,
      "close": 91.5,
      "change": -4.8,
      "transactions": 3941,
      "note": ""
    },
    {
      "date": "114/07/16",
      "volume": 2606997,
      "amount": 238743225,
      "open": 91.8,
      "high": 92.4,
      "low": 90.7,
      "close": 91.5,
      "change": 0.0,
      "transactions": 2147,
      "note": ""
    },
    {
      "date": "114/07/17",
      "volume": 2127316,
      "amount": 195726974,
      "open": 91.5,
      "high": 92.9,
      "low": 91.4,
      "close": 91.8,
      "change": 0.3,
      "transactions": 1781,
      "note": ""
    },
    {
      "date": "114/07/18",
      "volume": 2914432,
      "amount": 266802758,
      "open": 92.9,
      "high": 93.3,
      "low": 90.8,
      "close": 90.8,
      "change": -1.0,
      "transactions": 2148,
      "note": ""
    },
    {
      "date": "114/07/21",
      "volume": 2113064,
      "amount": 191578320,
      "open": 90.9,
      "high": 91.4,
      "low": 90.3,
      "close": 90.3,
      "change": -0.5,
      "transactions": 1804,
      "note": ""
    },
    {
      "date": "114/07/22",
      "volume": 2587236,
      "amount": 231518393,
      "open": 90.8,
      "high": 91.1,
      "low": 88.3,
      "close": 88.8,
      "change": -1.5,
      "transactions": 2107,
      "note": ""
    },
    {
      "date": "114/07/23",
      "volume": 1208318,
      "amount": 108445373,
      "open": 89.0,
      "high": 90.7,
      "low": 89.0,
      "close": 90.0,
      "change": 1.2,
      "transactions": 1243,
      "note": ""
    },
    {
      "date": "114/07/24",
      "volume": 1139533,
      "amount": 101660281,
      "open": 90.6,
      "high": 90.6,
      "low": 88.8,
      "close": 89.6,
      "change": -0.4,
      "transactions": 1225,
      "note": ""
    },
    {
      "date": "114/07/25",
      "volume": 818795,
      "amount": 73201641,
      "open": 89.6,
      "high": 89.9,
      "low": 88.8,
      "close": 89.9,
      "change": 0.3,
      "transactions": 819,
      "note": ""
    },
    {
      "date": "114/07/28",
      "volume": 3078682,
      "amount": 287303465,
      "open": 91.0,
      "high": 95.0,
      "low": 90.5,
      "close": 94.0,
      "change": 4.1,
      "transactions": 2487,
      "note": ""
    },
    {
      "date": "114/07/29",
      "volume": 1622949,
      "amount": 151360444,
      "open": 94.0,
      "high": 95.0,
      "low": 92.3,
      "close": 92.7,
      "change": -1.3,
      "transactions": 2260,
      "note": ""
    },
    {
      "date": "114/07/30",
      "volume": 666784,
      "amount": 61955285,
      "open": 94.1,
      "high": 94.1,
      "low": 92.3,
      "close": 93.2,
      "change": 0.5,
      "transactions": 1010,
      "note": ""
    },
    {
      "date": "114/07/31",
      "volume": 1869153,
      "amount": 176273971,
      "open": 92.9,
      "high": 95.1,
      "low": 92.3,
      "close": 94.6,
      "change": 1.4,
      "transactions": 2087,
      "note": ""
    }
  ]
}