{
  "stock_no": "6271",
  "year_month": "202602",
  "daily_data": [
    {
      "date": "115/02/02",
      "volume": 5736042,
      "amount": 784602526,
      "open": 138.5,
      "high": 141.5,
      "low": 134.0,
      "close": 136.0,
      "change": -4.5,
      "transactions": 4861,
      "note": ""
    },
    {
      "date": "115/02/03",
      "volume": 5611592,
      "amount": 805277934,
      "open": 140.0,
      "high": 147.5,
      "low": 139.5,
      "close": 143.0,
      "change": 7.0,
      "transactions": 5628,
      "note": ""
    }
  ]
}