{
  "stock_no": "1231",
  "year_month": "202503",
  "daily_data": [
    {
      "date": "114/03/03",
      "volume": 2755403,
      "amount": 368986914,
      "open": 139.5,
      "high": 140.0,
      "low": 130.0,
      "close": 130.5,
      "change": -10.5,
      "transactions": 5059,
      "note": ""
    },
    {
      "date": "114/03/04",
      "volume": 2347159,
      "amount": 303758483,
      "open": 127.0,
      "high": 133.0,
      "low": 124.5,
      "close": 131.5,
      "change": 1.0,
      "transactions": 3137,
      "note": ""
    },
    {
      "date": "114/03/05",
      "volume": 1453479,
      "amount": 194259751,
      "open": 131.0,
      "high": 136.0,
      "low": 131.0,
      "close": 133.5,
      "change": 2.0,
      "transactions": 2197,
      "note": ""
    },
    {
      "date": "114/03/06",
      "volume": 1755486,
      "amount": 245695918,
      "open": 138.5,
      "high": 142.5,
      "low": 137.0,
      "close": 141.5,
      "change": 8.0,
      "transactions": 2503,
      "note": ""
    },
    {
      "date": "114/03/07",
      "volume": 691553,
      "amount": 96953897,
      "open": 139.0,
      "high": 142.0,
      "low": 138.0,
      "close": 141.0,
      "change": -0.5,
      "transactions": 3165,
      "note": ""
    },
    {
      "date": "114/03/10",
      "volume": 1028546,
      "amount": 149092105,
      "open": 141.0,
      "high": 147.5,
      "low": 141.0,
      "close": 146.5,
      "change": 5.5,
      "transactions": 2151,
      "note": ""
    },
    {
      "date": "114/03/11",
      "volume": 1184299,
      "amount": 166100461,
      "open": 143.0,
      "high": 143.0,
      "low": 138.0,
      "close": 139.0,
      "change": -7.5,
      "transactions": 2408,
      "note": ""
    },
    {
      "date": "114/03/12",
      "volume": 1120234,
      "amount": 150834640,
      "open": 135.5,
      "high": 136.0,
      "low": 133.0,
      "close": 134.5,
      "change": -4.5,
      "transactions": 2222,
      "note": ""
    },
    {
      "date": "114/03/13",
      "volume": 885365,
      "amount": 118093022,
      "open": 133.0,
      "high": 136.5,
      "low": 131.5,
      "close": 131.5,
      "change": -3.0,
      "transactions": 2093,
      "note": ""
    },
    {
      "date": "114/03/14",
      "volume": 591340,
      "amount": 78548427,
      "open": 133.5,
      "high": 135.0,
      "low": 131.0,
      "close": 133.0,
      "change": 1.5,
      "transactions": 1007,
      "note": ""
    },
    {
      "date": "114/03/17",
      "volume": 401253,
      "amount": 53846317,
      "open": 133.5,
      "high": 136.0,
      "low": 133.0,
      "close": 133.0,
      "change": 0.0,
      "transactions": 768,
      "note": ""
    },
    {
      "date": "114/03/18",
      "volume": 377303,
      "amount": 50905115,
      "open": 133.0,
      "high": 136.0,
      "low": 133.0,
      "close": 135.0,
      "change": 2.0,
      "transactions": 677,
      "note": ""
    },
    {
      "date": "114/03/19",
      "volume": 531912,
      "amount": 71541701,
      "open": 135.0,
      "high": 137.5,
      "low": 132.5,
      "close": 132.5,
      "change": -2.5,
      "transactions": 888,
      "note": ""
    },
    {
      "date": "114/03/20",
      "volume": 533450,
      "amount": 71954463,
      "open": 132.5,
      "high": 136.5,
      "low": 132.5,
      "close": 135.0,
      "change": 2.5,
      "transactions": 663,
      "note": ""
    },
    {
      "date": "114/03/21",
      "volume": 3130898,
      "amount": 413639819,
      "open": 135.0,
      "high": 135.0,
      "low": 131.0,
      "close": 132.0,
      "change": -3.0,
      "transactions": 1374,
      "note": ""
    },
    {
      "date": "114/03/24",
      "volume": 709161,
      "amount": 92996380,
      "open": 131.5,
      "high": 134.0,
      "low": 129.5,
      "close": 129.5,
      "change": -2.5,
      "transactions": 1514,
      "note": ""
    },
    {
      "date": "114/03/25",
      "volume": 432367,
      "amount": 56625891,
      "open": 131.5,
      "high": 132.5,
      "low": 129.0,
      "close": 131.5,
      "change": 2.0,
      "transactions": 919,
      "note": ""
    },
    {
      "date": "114/03/26",
      "volume": 317500,
      "amount": 42647121,
      "open": 133.0,
      "high": 135.5,
      "low": 132.5,
      "close": 134.5,
      "change": 3.0,
      "transactions": 608,
      "note": ""
    },
    {
      "date": "114/03/27",
      "volume": 432428,
      "amount": 58522852,
      "open": 132.5,
      "high": 137.0,
      "low": 132.5,
      "close": 135.0,
      "change": 0.5,
      "transactions": 752,
      "note": ""
    },
    {
      "date": "114/03/28",
      "volume": 381592,
      "amount": 50336575,
      "open": 134.0,
      "high": 134.5,
      "low": 130.5,
      "close": 131.0,
      "change": -4.0,
      "transactions": 1328,
      "note": ""
    },
    {
      "date": "114/03/31",
      "volume": 445091,
      "amount": 57032021,
      "open": 126.5,
      "high": 129.5,
      "low": 126.5,
      "close": 127.5,
      "change": -3.5,
      "transactions": 1336,
      "note": ""
    }
  ]
}