{
  "stock_no": "3058",
  "year_month": "202506",
  "daily_data": [
    {
      "date": "114/06/02",
      "volume": 561429,
      "amount": 5493440,
      "open": 10.05,
      "high": 10.2,
      "low": 9.6,
      "close": 9.67,
      "change": -0.38,
      "transactions": 560,
      "note": ""
    },
    {
      "date": "114/06/03",
      "volume": 794288,
      "amount": 7784968,
      "open": 9.8,
      "high": 10.2,
      "low": 9.6,
      "close": 9.73,
      "change": 0.06,
      "transactions": 437,
      "note": ""
    },
    {
      "date": "114/06/04",
      "volume": 364496,
      "amount": 3606577,
      "open": 9.81,
      "high": 10.0,
      "low": 9.79,
      "close": 9.81,
      "change": 0.08,
      "transactions": 295,
      "note": ""
    },
    {
      "date": "114/06/05",
      "volume": 207839,
      "amount": 2048916,
      "open": 9.84,
      "high": 9.92,
      "low": 9.8,
      "close": 9.8,
      "change": -0.01,
      "transactions": 236,
      "note": ""
    },
    {
      "date": "114/06/06",
      "volume": 321657,
      "amount": 3131940,
      "open": 9.79,
      "high": 9.8,
      "low": 9.7,
      "close": 9.71,
      "change": -0.09,
      "transactions": 350,
      "note": ""
    },
    {
      "date": "114/06/09",
      "volume": 1050023,
      "amount": 10070666,
      "open": 9.7,
      "high": 9.83,
      "low": 9.38,
      "close": 9.75,
      "change": 0.04,
      "transactions": 1395,
      "note": ""
    },
    {
      "date": "114/06/10",
      "volume": 354079,
      "amount": 3458533,
      "open": 9.75,
      "high": 9.82,
      "low": 9.6,
      "close": 9.76,
      "change": 0.01,
      "transactions": 464,
      "note": ""
    },
    {
      "date": "114/06/11",
      "volume": 523476,
      "amount": 5080789,
      "open": 9.76,
      "high": 9.76,
      "low": 9.65,
      "close": 9.74,
      "change": -0.02,
      "transactions": 361,
      "note": ""
    },
    {
      "date": "114/06/12",
      "volume": 487557,
      "amount": 4682786,
      "open": 9.8,
      "high": 9.8,
      "low": 9.51,
      "close": 9.59,
      "change": -0.15,
      "transactions": 424,
      "note": ""
    },
    {
      "date": "114/06/13",
      "volume": 658238,
      "amount": 6204042,
      "open": 9.59,
      "high": 9.59,
      "low": 9.34,
      "close": 9.37,
      "change": -0.22,
      "transactions": 621,
      "note": ""
    },
    {
      "date": "114/06/16",
      "volume": 259420,
      "amount": 2433050,
      "open": 9.37,
      "high": 9.47,
      "low": 9.26,
      "close": 9.38,
      "change": 0.01,
      "transactions": 263,
      "note": ""
    },
    {
      "date": "114/06/17",
      "volume": 283001,
      "amount": 2697617,
      "open": 9.8,
      "high": 9.8,
      "low": 9.43,
      "close": 9.65,
      "change": 0.27,
      "transactions": 269,
      "note": ""
    },
    {
      "date": "114/06/18",
      "volume": 334962,
      "amount": 3218159,
      "open": 9.63,
      "high": 9.66,
      "low": 9.51,
      "close": 9.58,
      "change": -0.07,
      "transactions": 338,
      "note": ""
    },
    {
      "date": "114/06/19",
      "volume": 398782,
      "amount": 3745553,
      "open": 9.48,
      "high": 9.55,
      "low": 9.33,
      "close": 9.34,
      "change": -0.24,
      "transactions": 449,
      "note": ""
    },
    {
      "date": "114/06/20",
      "volume": 523433,
      "amount": 4852410,
      "open": 9.31,
      "high": 9.48,
      "low": 9.12,
      "close": 9.46,
      "change": 0.12,
      "transactions": 573,
      "note": ""
    },
    {
      "date": "114/06/23",
      "volume": 589149,
      "amount": 5402244,
      "open": 9.45,
      "high": 9.45,
      "low": 9.11,
      "close": 9.17,
      "change": -0.29,
      "transactions": 578,
      "note": ""
    },
    {
      "date": "114/06/24",
      "volume": 417849,
      "amount": 3935253,
      "open": 9.26,
      "high": 9.55,
      "low": 9.22,
      "close": 9.42,
      "change": 0.25,
      "transactions": 285,
      "note": ""
    },
    {
      "date": "114/06/25",
      "volume": 1210177,
      "amount": 11990051,
      "open": 9.42,
      "high": 10.2,
      "low": 9.4,
      "close": 10.0,
      "change": 0.58,
      "transactions": 932,
      "note": ""
    },
    {
      "date": "114/06/26",
      "volume": 871168,
      "amount": 8773545,
      "open": 10.0,
      "high": 10.3,
      "low": 9.95,
      "close": 10.0,
      "change": 0.0,
      "transactions": 578,
      "note": ""
    },
    {
      "date": "114/06/27",
      "volume": 522054,
      "amount": 5208485,
      "open": 9.99,
      "high": 10.05,
      "low": 9.93,
      "close": 9.93,
      "change": -0.07,
      "transactions": 376,
      "note": ""
    },
    {
      "date": "114/06/30",
      "volume": 405141,
      "amount": 3929099,
      "open": 10.1,
      "high": 10.1,
      "low": 9.6,
      "close": 9.64,
      "change": -0.29,
      "transactions": 358,
      "note": ""
    }
  ]
}