{
  "stock_no": "2062",
  "year_month": "202508",
  "daily_data": [
    {
      "date": "114/08/01",
      "volume": 302811,
      "amount": 7342570,
      "open": 24.15,
      "high": 24.5,
      "low": 23.85,
      "close": 24.4,
      "change": 0.25,
      "transactions": 219,
      "note": ""
    },
    {
      "date": "114/08/04",
      "volume": 444655,
      "amount": 11017179,
      "open": 24.3,
      "high": 25.1,
      "low": 24.15,
      "close": 25.0,
      "change": 0.6,
      "transactions": 306,
      "note": ""
    },
    {
      "date": "114/08/05",
      "volume": 266335,
      "amount": 6657388,
      "open": 25.25,
      "high": 25.25,
      "low": 24.8,
      "close": 24.85,
      "change": -0.15,
      "transactions": 220,
      "note": ""
    },
    {
      "date": "114/08/06",
      "volume": 214451,
      "amount": 5351653,
      "open": 24.85,
      "high": 25.05,
      "low": 24.8,
      "close": 24.9,
      "change": 0.05,
      "transactions": 158,
      "note": ""
    },
    {
      "date": "114/08/07",
      "volume": 389873,
      "amount": 9772804,
      "open": 25.0,
      "high": 25.15,
      "low": 24.9,
      "close": 25.1,
      "change": 0.2,
      "transactions": 270,
      "note": ""
    },
    {
      "date": "114/08/08",
      "volume": 353723,
      "amount": 8965492,
      "open": 25.1,
      "high": 25.55,
      "low": 25.1,
      "close": 25.25,
      "change": 0.15,
      "transactions": 302,
      "note": ""
    },
    {
      "date": "114/08/11",
      "volume": 247395,
      "amount": 6182005,
      "open": 25.5,
      "high": 25.5,
      "low": 24.85,
      "close": 24.9,
      "change": -0.35,
      "transactions": 207,
      "note": ""
    },
    {
      "date": "114/08/12",
      "volume": 375911,
      "amount": 9285132,
      "open": 24.95,
      "high": 24.95,
      "low": 24.45,
      "close": 24.5,
      "change": -0.4,
      "transactions": 291,
      "note": ""
    },
    {
      "date": "114/08/13",
      "volume": 385129,
      "amount": 9515499,
      "open": 24.8,
      "high": 25.1,
      "low": 24.35,
      "close": 24.75,
      "change": 0.25,
      "transactions": 272,
      "note": ""
    },
    {
      "date": "114/08/14",
      "volume": 294808,
      "amount": 7399507,
      "open": 24.7,
      "high": 25.3,
      "low": 24.7,
      "close": 25.05,
      "change": 0.3,
      "transactions": 250,
      "note": ""
    },
    {
      "date": "114/08/15",
      "volume": 770414,
      "amount": 19722473,
      "open": 25.2,
      "high": 25.85,
      "low": 25.15,
      "close": 25.7,
      "change": 0.65,
      "transactions": 509,
      "note": ""
    },
    {
      "date": "114/08/18",
      "volume": 587312,
      "amount": 15100669,
      "open": 25.6,
      "high": 26.1,
      "low": 25.45,
      "close": 25.55,
      "change": -0.15,
      "transactions": 412,
      "note": ""
    },
    {
      "date": "114/08/19",
      "volume": 503213,
      "amount": 12989531,
      "open": 25.75,
      "high": 26.05,
      "low": 25.65,
      "close": 25.7,
      "change": 0.15,
      "transactions": 315,
      "note": ""
    },
    {
      "date": "114/08/20",
      "volume": 445246,
      "amount": 11354965,
      "open": 25.7,
      "high": 25.7,
      "low": 25.35,
      "close": 25.5,
      "change": -0.2,
      "transactions": 308,
      "note": ""
    },
    {
      "date": "114/08/21",
      "volume": 1015484,
      "amount": 26404886,
      "open": 25.7,
      "high": 26.35,
      "low": 25.7,
      "close": 25.85,
      "change": 0.35,
      "transactions": 571,
      "note": ""
    },
    {
      "date": "114/08/22",
      "volume": 484681,
      "amount": 12475762,
      "open": 25.85,
      "high": 26.05,
      "low": 25.5,
      "close": 25.7,
      "change": -0.15,
      "transactions": 255,
      "note": ""
    },
    {
      "date": "114/08/25",
      "volume": 538389,
      "amount": 13931626,
      "open": 25.7,
      "high": 26.1,
      "low": 25.7,
      "close": 25.85,
      "change": 0.15,
      "transactions": 292,
      "note": ""
    },
    {
      "date": "114/08/26",
      "volume": 669521,
      "amount": 17146035,
      "open": 25.85,
      "high": 25.9,
      "low": 25.45,
      "close": 25.45,
      "change": -0.4,
      "transactions": 432,
      "note": ""
    },
    {
      "date": "114/08/27",
      "volume": 1124196,
      "amount": 28869973,
      "open": 25.5,
      "high": 25.9,
      "low": 25.5,
      "close": 25.65,
      "change": 0.2,
      "transactions": 622,
      "note": ""
    },
    {
      "date": "114/08/28",
      "volume": 1463697,
      "amount": 34594990,
      "open": 23.85,
      "high": 23.95,
      "low": 23.35,
      "close": 23.55,
      "change": 0.0,
      "transactions": 761,
      "note": ""
    },
    {
      "date": "114/08/29",
      "volume": 846852,
      "amount": 19637034,
      "open": 23.55,
      "high": 23.55,
      "low": 23.0,
      "close": 23.15,
      "change": -0.4,
      "transactions": 495,
      "note": ""
    }
  ]
}